langchain_imap/__init__.py
langchain_imap/py.typed
langchain_imap/retrievers.py
langchain_imap/utils.py
langchain_imap-0.1.0.dist-info/METADATA
langchain_imap-0.1.0.dist-info/WHEEL
langchain_imap-0.1.0.dist-info/licenses/LICENSE
langchain_imap-0.1.0.dist-info/RECORD
