Metadata-Version: 2.4
Name: langchain-imap
Version: 0.1.0
Summary: LangChain integration for retrieving emails from IMAP servers
License: MIT
License-File: LICENSE
Author: Julien FOURET
Author-email: julien.fouret@univ-lyon1.fr
Requires-Python: >=3.11,<4.0
Classifier: License :: OSI Approved :: MIT License
Classifier: Programming Language :: Python :: 3
Classifier: Programming Language :: Python :: 3.11
Classifier: Programming Language :: Python :: 3.12
Classifier: Programming Language :: Python :: 3.13
Classifier: Programming Language :: Python :: 3.14
Provides-Extra: docling
Requires-Dist: docling (>=2.54.0,<3.0.0) ; extra == "docling"
Requires-Dist: html-to-markdown (>=1.14.1,<2.0.0)
Requires-Dist: langchain-core (>=0.3.15,<0.4.0)
Requires-Dist: pypdf (>=6.1.1,<7.0.0)
Requires-Dist: pyyaml (>=6.0,<7.0)
Project-URL: Repository, https://github.com/langchain-ai/langchain
Project-URL: Release Notes, https://github.com/langchain-ai/langchain/releases?q=tag%3A%22imap%3D%3D0%22&expanded=true
Project-URL: Source Code, https://github.com/langchain-ai/langchain/tree/master/libs/partners/imap
